{
  "voe": {
    "operators": [
      "RBO",
      "VGM",
      "DVB",
      "RVSOE",
      "SATRA",
      "Müller Busreisen",
      "SDG",
      "Schmidt-Reisen",
      "VGH"
    ]
  },
  "vbb": {
    "operators": [
      "ODEG Ostdeutsche Eisenbahn GmbH",
      "DB Regio Bus Ost GmbH",
      "DB Regio AG",
      "Verkehrsmanagement Elbe-Elster GmbH",
      "Verkehrsgesellschaft Oberspreewald-Lausitz mbH"
    ]
  },
  "ddb": {
    "operators": [
      "Ostdeutsche Eisenbahn GmbH",
      "trilex - Die Länderbahn GmbH DLB",
      "Sächsisch-Oberlausitzer Eisenbahngesellschaft",
      "DB AG",
      "DB Regio AG Südost",
      "Mitteldeutsche Regiobahn",
      "SDG Sächsische Dampfeisenbahngesellschaft mbH",
      "Freiberger Eisenbahngesellschaft",
      "Ceske Drahy"
    ]
  },
  "nas": {
    "operators": [
      "Nordsachsen Mobil",
      "DB Regio AG Nordost"
    ]
  },
  "vms": {
    "operators": [
      "RBM",
      "RVE"
    ]
  }
}